optr/__init__.py
optr/py.typed
optr/algorithms/__init__.py
optr/algorithms/base.py
optr/algorithms/registry.py
optr/algorithms/imitation/__init__.py
optr/algorithms/imitation/imitation.py
optr/algorithms/pi0/__init__.py
optr/algorithms/pi0/flow.py
optr/algorithms/pi0/moe.py
optr/algorithms/pi0/pi0.py
optr/algorithms/pi0/vlm/__init__.py
optr/algorithms/pi0/vlm/base.py
optr/algorithms/pi0/vlm/paligemma.py
optr/algorithms/pi0/vlm/simple.py
optr/algorithms/pi0/vlm/tokenizer.py
optr/connector/__init__.py
optr/connector/base.py
optr/connector/desktop/__init__.py
optr/connector/desktop/base.py
optr/connector/desktop/linux.py
optr/connector/desktop/macos.py
optr/core/__init__.py
optr/core/io/__init__.py
optr/core/io/iterator.py
optr/core/io/protocols.py
optr/core/io/test_io.py
optr/core/io/writer/__init__.py
optr/core/io/writer/background.py
optr/core/io/writer/protocols.py
optr/core/io/writer/test_background.py
optr/core/ipc/sharedframe.py
optr/core/ipc/test_sharedframe.py
optr/core/protocols/__init__.py
optr/core/protocols/communication.py
optr/cortex/__init__.py
optr/cortex/critic.py
optr/cortex/memory.py
optr/cortex/planner.py
optr/input/__init__.py
optr/input/keyboard.py
optr/input/socket.py
optr/ledger/__init__.py
optr/ledger/episode.py
optr/ledger/recorder.py
optr/ledger/solana/__init__.py
optr/ledger/solana/action.py
optr/ledger/solana/batch.py
optr/ledger/solana/chain.py
optr/ledger/solana/serialize.py
optr/ledger/solana/wallet.py
optr/media/__init__.py
optr/media/fps.py
optr/media/mp4.py
optr/media/test_mp4.py
optr/media/gstreamer/__init__.py
optr/media/gstreamer/caps.py
optr/media/gstreamer/errors.py
optr/media/gstreamer/readers.py
optr/media/gstreamer/writers.py
optr/media/gstreamer/buffer/__init__.py
optr/media/gstreamer/buffer/core.py
optr/media/gstreamer/buffer/errors.py
optr/media/gstreamer/buffer/pool.py
optr/media/gstreamer/buffer/zerocopy.py
optr/media/gstreamer/control/__init__.py
optr/media/gstreamer/control/loop.py
optr-0.0.0a12.dist-info/METADATA
optr-0.0.0a12.dist-info/WHEEL
optr-0.0.0a12.dist-info/licenses/LICENSE.md
optr-0.0.0a12.dist-info/RECORD
