Metadata-Version: 2.4
Name: optr
Version: 0.0.0a12
Summary: Unified toolkit for building, training, and testing digital and physical operators.
Project-URL: Repository, https://github.com/codecflow/optr
Project-URL: Issues, https://github.com/codecflow/optr/issues
Author-email: CodecFlow Team <team@codecflow.ai>
License: MIT
License-File: LICENSE.md
Keywords: automation,desktop,operators,robotics,sdk,simulation
Classifier: Development Status :: 3 - Alpha
Classifier: Intended Audience :: Developers
Classifier: Intended Audience :: Science/Research
Classifier: License :: OSI Approved :: MIT License
Classifier: Operating System :: OS Independent
Classifier: Topic :: Scientific/Engineering :: Artificial Intelligence
Classifier: Topic :: Software Development :: Libraries :: Python Modules
Classifier: Typing :: Typed
Requires-Python: >=3.12
Requires-Dist: numpy
Provides-Extra: desktop
Requires-Dist: mss; extra == 'desktop'
Requires-Dist: pyautogui; extra == 'desktop'
Requires-Dist: types-pyautogui; extra == 'desktop'
Provides-Extra: image
Requires-Dist: imageio; extra == 'image'
Requires-Dist: pillow; extra == 'image'
Provides-Extra: inference
Requires-Dist: onnxruntime; extra == 'inference'
Provides-Extra: ocr
Requires-Dist: pytesseract; extra == 'ocr'
Provides-Extra: simulation
Requires-Dist: mujoco; extra == 'simulation'
Provides-Extra: solana
Requires-Dist: anchorpy; extra == 'solana'
Requires-Dist: base58; extra == 'solana'
Requires-Dist: msgpack; extra == 'solana'
Requires-Dist: solana; extra == 'solana'
Requires-Dist: solders; extra == 'solana'
Provides-Extra: streaming
Requires-Dist: pygobject; extra == 'streaming'
Provides-Extra: training
Requires-Dist: torch; extra == 'training'
Requires-Dist: torchvision; extra == 'training'
Requires-Dist: transformers; extra == 'training'
Provides-Extra: video
Requires-Dist: imageio[ffmpeg]; extra == 'video'
Provides-Extra: vision
Requires-Dist: opencv-python; extra == 'vision'
